pyvanguard/__init__.py
pyvanguard/cli.py
pyvanguard/command/__init__.py
pyvanguard/command/alert.py
pyvanguard/command/load.py
pyvanguard/command/query.py
pyvanguard/core/__init__.py
pyvanguard/core/mind.py
pyvanguard/exception/__init__.py
pyvanguard/module/__init__.py
pyvanguard/module/database.py
pyvanguard/module/file_system.py
pyvanguard/module/logger.py
pyvanguard/module/openai.py
pyvanguard/module/pagerduty.py
pyvanguard/module/qdrant.py
pyvanguard/module/util.py
pyvanguard-0.2.0.dist-info/LICENSE.txt
pyvanguard-0.2.0.dist-info/METADATA
pyvanguard-0.2.0.dist-info/WHEEL
pyvanguard-0.2.0.dist-info/entry_points.txt
pyvanguard-0.2.0.dist-info/top_level.txt
pyvanguard-0.2.0.dist-info/RECORD
