Metadata-Version: 2.2
Name: pyvanguard
Version: 0.2.0
Summary: OnCall AI Assistant, Your Intelligent Incident Resolution Partner!
Home-page: https://github.com/Clivern/PyVanguard/
Author: clivern
Author-email: hello@clivern.com
License: MIT
Project-URL: Documentation, https://github.com/Clivern/PyVanguard/
Project-URL: Source, https://github.com/Clivern/PyVanguard/
Project-URL: Changelog, https://github.com/Clivern/PyVanguard/blob/main/CHANGELOG.rst
Project-URL: Tracker, https://github.com/Clivern/PyVanguard/issues
Project-URL: Download, https://pypi.org/project/PyVanguard/#files
Platform: any
Classifier: Development Status :: 5 - Production/Stable
Classifier: Programming Language :: Python
Classifier: License :: OSI Approved :: MIT License
License-File: LICENSE.txt
Requires-Dist: click<=8.1.8
Requires-Dist: rich<=13.9.4
Requires-Dist: openai<=1.63.2
Requires-Dist: qdrant-client<=1.13.2
Requires-Dist: requests<=2.32.3
Requires-Dist: langchain<=0.3.19
Requires-Dist: langchain-openai<=0.3.6
Requires-Dist: importlib-metadata<=8.6.1; python_version < "3.8"
